setup.py
distributions/Binomialdistribution.py
distributions/Gaussiandistribution.py
distributions/Generaldistribution.py
distributions/__init__.py
simple_nb_distributions.egg-info/PKG-INFO
simple_nb_distributions.egg-info/SOURCES.txt
simple_nb_distributions.egg-info/dependency_links.txt
simple_nb_distributions.egg-info/not-zip-safe
simple_nb_distributions.egg-info/top_level.txt